README.md
setup.py
fjell/__init__.py
fjell/app.py
fjell/config.py
fjell/http.py
fjell/locator.py
fjell/test.py
fjell/views.py
fjell.egg-info/PKG-INFO
fjell.egg-info/SOURCES.txt
fjell.egg-info/dependency_links.txt
fjell.egg-info/requires.txt
fjell.egg-info/top_level.txt
fjell/plugins/__init__.py
fjell/plugins/jinja2.py
fjell/plugins/sqla.py