Metadata-Version: 2.1
Name: fjell
Version: 0.1.1
Summary: A web framework.
Home-page: https://github.com/anlutro/fjell.py
Author: Andreas Lutro
Author-email: anlutro@gmail.com
License: MIT
Keywords: web,framework
Platform: UNKNOWN
Classifier: Development Status :: 4 - Beta
Classifier: Intended Audience :: Developers
Classifier: Operating System :: POSIX
Classifier: Programming Language :: Python
Classifier: Programming Language :: Python :: 3.5
Classifier: Programming Language :: Python :: 3.6
Classifier: Programming Language :: Python :: 3.7
